aquareflog.py
aquaref_log-0.0.1.dist-info/METADATA
aquaref_log-0.0.1.dist-info/WHEEL
aquaref_log-0.0.1.dist-info/RECORD
